pikabu_bot
