Metadata-Version: 1.0
Name: pikabu-telegram-bot
Version: 0.1.8
Summary: Pikabu bot for telegram. Powered by python-telegram-bot
Home-page: UNKNOWN
Author: Alexey Kalyaganov
Author-email: admin@futurobot.ru
License: LGPLv3
Platform: UNKNOWN
